django_zhanchi/__init__.py
django_zhanchi/main.py
django_zhanchi-0.1.0.dist-info/WHEEL
django_zhanchi-0.1.0.dist-info/METADATA
django_zhanchi-0.1.0.dist-info/RECORD
