Metadata-Version: 2.1
Name: django-zhanchi
Version: 0.1.0
Summary: 
Author: Furkan Karataş
Author-email: furkan.karatas02@gmail.com
Requires-Python: >=3.8,<4.0
Classifier: Programming Language :: Python :: 3
Classifier: Programming Language :: Python :: 3.8
Requires-Dist: requests (>=2.24.0,<3.0.0)
